ahbichtfunctionsclient/__init__.py
ahbichtfunctionsclient/py.typed
ahbichtfunctionsclient-0.0.5.dist-info/LICENSE
ahbichtfunctionsclient-0.0.5.dist-info/METADATA
ahbichtfunctionsclient-0.0.5.dist-info/WHEEL
ahbichtfunctionsclient-0.0.5.dist-info/top_level.txt
ahbichtfunctionsclient-0.0.5.dist-info/RECORD
