Metadata-Version: 2.1
Name: ahbichtfunctionsclient
Version: 0.0.5
Summary: A lightweight client for an AHBicht powered Backend
Home-page: https://github.com/Hochfrequenz/ahbicht-functions-python-client
Author: Hochfrequenz Unternehmensberatung GmbH
Author-email: info@hochfrequenz.de
License: mit
Project-URL: Documentation, https://github.com/Hochfrequenz/ahbicht-functions-python-client
Project-URL: Code, https://github.com/Hochfrequenz/ahbicht-functions-python-client
Project-URL: Bug tracker, https://github.com/Hochfrequenz/ahbicht-functions-python-client/issues
Platform: any
Classifier: Development Status :: 4 - Beta
Classifier: Intended Audience :: Developers
Classifier: Programming Language :: Python
Classifier: Programming Language :: Python :: 3.9
Classifier: Operating System :: OS Independent
Requires-Python: >=3.8
Requires-Dist: ahbicht
Requires-Dist: aiohttp
